weather_collector/__init__.py
weather_collector/sampler.py
weather_collector/weather_collection.py
weather_collector/weather_endpoints.py
weather_collector-0.2.5.dist-info/METADATA
weather_collector-0.2.5.dist-info/WHEEL
weather_collector-0.2.5.dist-info/entry_points.txt
weather_collector-0.2.5.dist-info/top_level.txt
weather_collector-0.2.5.dist-info/RECORD
