Metadata-Version: 2.1
Name: weather-collector
Version: 0.2.5
Summary: CLI for collecting weather data
Home-page: https://codeberg.org/cap_jmk/weather-collector
Author: Julian M. Kleber
Author-email: julian.kleber@sail.black
Classifier: Programming Language :: Python :: 3
Classifier: License :: OSI Approved :: GNU General Public License v3 (GPLv3)
Classifier: Operating System :: OS Independent
Requires-Python: >=3.9
Requires-Dist: Click
Requires-Dist: bulkhead
Requires-Dist: amarium
